{"nodes":[{"id":"design_sodosans","label":"SoDoSans Typeface","file_type":"document","source_file":"DESIGN.md"},{"id":"design_starbucks_green","label":"Starbucks Green","file_type":"document","source_file":"DESIGN.md"},{"id":"design_green_accent","label":"Green Accent","file_type":"document","source_file":"DESIGN.md"},{"id":"design_frap_cta","label":"Frap Floating CTA","file_type":"document","source_file":"DESIGN.md"},{"id":"design_gold","label":"Gold","file_type":"document","source_file":"DESIGN.md"},{"id":"design_rewards_ceremony","label":"Rewards Ceremony","file_type":"document","source_file":"DESIGN.md"},{"id":"design_confident_friendly_voice","label":"Confident Friendly Voice","file_type":"document","source_file":"DESIGN.md"},{"id":"master_sodosans","label":"SoDoSans Typeface","file_type":"document","source_file":"design-system/MASTER.md"},{"id":"readme_vite_react","label":"@vitejs/plugin-react","file_type":"document","source_file":"README.md"},{"id":"readme_eslint_config","label":"ESLint Configuration","file_type":"document","source_file":"README.md"},{"id":"index_main_tsx","label":"main.tsx","file_type":"code","source_file":"index.html"},{"id":"index_root_div","label":"root div","file_type":"code","source_file":"index.html"},{"id":"b64_base64_content","label":"Base64 Design System","file_type":"document","source_file":"b64.txt"},{"id":"b64_wrapped_base64_content","label":"Wrapped Base64 Design System","file_type":"document","source_file":"b64_wrapped.txt"},{"id":"favicon_svg","label":"Favicon","file_type":"image","source_file":"public/favicon.svg"},{"id":"icons_svg","label":"Icons Spritesheet","file_type":"image","source_file":"public/icons.svg"},{"id":"hero_image","label":"Hero Image","file_type":"image","source_file":"src/assets/hero.png"},{"id":"react_logo","label":"React Logo","file_type":"image","source_file":"src/assets/react.svg"},{"id":"vite_logo","label":"Vite Logo","file_type":"image","source_file":"src/assets/vite.svg"}],"edges":[{"source":"design_sodosans","target":"design_confident_friendly_voice","relation":"rationale_for","confidence":"EXTRACTED","confidence_score":1.0,"source_file":"DESIGN.md"},{"source":"design_gold","target":"design_rewards_ceremony","relation":"conceptually_related_to","confidence":"EXTRACTED","confidence_score":1.0,"source_file":"DESIGN.md"},{"source":"design_green_accent","target":"design_frap_cta","relation":"conceptually_related_to","confidence":"EXTRACTED","confidence_score":1.0,"source_file":"DESIGN.md"},{"source":"design_sodosans","target":"master_sodosans","relation":"semantically_similar_to","confidence":"INFERRED","confidence_score":0.95,"source_file":"DESIGN.md"},{"source":"index_main_tsx","target":"index_root_div","relation":"conceptually_related_to","confidence":"INFERRED","confidence_score":0.85,"source_file":"index.html"},{"source":"readme_vite_react","target":"react_logo","relation":"conceptually_related_to","confidence":"INFERRED","confidence_score":0.8,"source_file":"README.md"},{"source":"readme_vite_react","target":"vite_logo","relation":"conceptually_related_to","confidence":"INFERRED","confidence_score":0.8,"source_file":"README.md"}],"hyperedges":[{"id":"design_starbucks_colors","label":"Starbucks Color Palette","nodes":["design_starbucks_green","design_green_accent","design_house_green","design_gold"],"relation":"form","confidence":"EXTRACTED","confidence_score":1.0,"source_file":"DESIGN.md"}],"input_tokens":0,"output_tokens":0}